aind_physiology_fip/__init__.py
aind_physiology_fip/cli.py
aind_physiology_fip/data_contract.py
aind_physiology_fip/data_mappers/__init__.py
aind_physiology_fip/data_mappers/_acquisition.py
aind_physiology_fip/data_mappers/_base.py
aind_physiology_fip/data_qc.py
aind_physiology_fip/data_qc_helpers.py
aind_physiology_fip/regenerate.py
aind_physiology_fip/rig.py
aind_physiology_fip-0.2.0.dist-info/WHEEL
aind_physiology_fip-0.2.0.dist-info/entry_points.txt
aind_physiology_fip-0.2.0.dist-info/METADATA
aind_physiology_fip-0.2.0.dist-info/RECORD
