Metadata-Version: 2.3
Name: aind-physiology-fip
Version: 0.2.0
Summary: A repository for Fiber Photometry data acquisition
Author: Bruno Cruz, Kenta Hagihara
Author-email: Bruno Cruz <bruno.cruz@alleninstitute.org>, Kenta Hagihara <kenta.hagihara@alleninstitute.org>
License: MIT
Classifier: Programming Language :: Python :: 3.11
Classifier: License :: OSI Approved :: MIT License
Classifier: Operating System :: Microsoft :: Windows
Requires-Dist: aind-behavior-services<0.13
Requires-Dist: contraqctor<0.6 ; extra == 'data'
Requires-Dist: pydantic-settings ; extra == 'data'
Requires-Dist: opencv-python ; extra == 'data'
Requires-Python: >=3.11
Project-URL: Changelog, https://github.com/AllenNeuralDynamics/Aind.Physiology.Fip/releases
Project-URL: Documentation, https://allenneuraldynamics.github.io/Aind.Physiology.Fip/
Project-URL: Issues, https://github.com/AllenNeuralDynamics/Aind.Physiology.Fip/issues
Project-URL: Repository, https://github.com/AllenNeuralDynamics/Aind.Physiology.Fip/
Provides-Extra: data
